<?xml version='1.0' encoding='utf-8'?>
<dataset><images><image file="/Users/juntianzhong/BioVision/images/claudio-guglieri-K2RH1QZdLF4-unsplash.jpg"><box top="170" left="216" width="434" height="268"><part name="0" x="234" y="205" /><part name="1" x="250" y="241" /><part name="2" x="258" y="205" /><part name="3" x="288" y="206" /><part name="4" x="305" y="186" /><part name="5" x="261" y="271" /></box></image><image file="/Users/juntianzhong/BioVision/images/rachel-hisko-rEM3cK8F1pk-unsplash.jpg"><box top="154" left="129" width="478" height="239"><part name="0" x="574" y="221" /><part name="1" x="563" y="230" /><part name="2" x="542" y="215" /><part name="3" x="517" y="218" /><part name="4" x="530" y="195" /><part name="5" x="549" y="278" /><part name="6" x="452" y="182" /><part name="7" x="432" y="161" /><part name="8" x="375" y="207" /><part name="9" x="472" y="259" /><part name="10" x="405" y="240" /><part name="11" x="490" y="315" /><part name="12" x="446" y="361" /><part name="13" x="353" y="217" /><part name="14" x="314" y="214" /><part name="15" x="276" y="282" /><part name="16" x="392" y="334" /><part name="17" x="317" y="374" /><part name="18" x="305" y="335" /><part name="19" x="240" y="294" /><part name="20" x="264" y="352" /><part name="21" x="163" y="314" /><part name="22" x="201" y="388" /></box></image></images></dataset>